[
    {
        "title": "Смартфон APPLE iPhone 13 Pro Max 128GB Sierra Blue (MLL93)",
        "author_name": "Алёна",
        "url": "https://eldorado.ua/smartfon-apple-iphone-13-pro-max-128gb-sierra-blue/p71357115/",
        "grade": 5,
        "date": "23.01.2022",
        "text": "APPLE iPhone 13 Pro Max 128GB современный стильный смартфон. Интернет работает нормально, нужные сайты обычно открываются быстро. Сенсор распознавания лица, есть беспроводная зарядка."
    },
    {
        "title": "Смартфон APPLE iPhone 13 Pro Max 128GB Sierra Blue (MLL93)",
        "author_name": "Ивана",
        "url": "https://eldorado.ua/smartfon-apple-iphone-13-pro-max-128gb-sierra-blue/p71357115/",
        "grade": 5,
        "date": "21.01.2022",
        "text": "Отлично снимает видео, очень достойная автономность, прекрасная работа фейс ID, за 3 месяца не одного глюка, очень стабильная работа по сравнению с андроид."
    },
    {
        "title": "Смартфон APPLE iPhone 13 Pro Max 128GB Sierra Blue (MLL93)",
        "author_name": "Игорь",
        "url": "https://eldorado.ua/smartfon-apple-iphone-13-pro-max-128gb-sierra-blue/p71357115/",
        "grade": 5,
        "date": "21.01.2022",
        "text": "Замечательный смартфон, суперская камера и наконец-то телефон держит заряд до позднего вечера.Отличный дизайн, 120Hz матрица, отличная цветопередача, качество материалов, режим \"киноэффект\"."
    },
    {
        "title": "Смартфон APPLE iPhone 13 Pro Max 128GB Sierra Blue (MLL93)",
        "author_name": "Павел",
        "url": "https://eldorado.ua/smartfon-apple-iphone-13-pro-max-128gb-sierra-blue/p71357115/",
        "grade": 5,
        "date": "21.01.2022",
        "text": "Ну вот и прошли первые дни пользования данным смартфоном и вот что могу сказать о нем. Смартфон очень приятно лежит в руках хоть он и достаточно большой. Порадовала его производительность в играх. Ещё меня очень привлекла видео съемка. Если вы ищете хорошо устройство как для игр фото и работы, тогда советую посмотреть на данный смартфон."
    },
    {
        "title": "Смартфон APPLE iPhone 13 Pro Max 128GB Sierra Blue (MLL93)",
        "author_name": "Милана",
        "url": "https://eldorado.ua/smartfon-apple-iphone-13-pro-max-128gb-sierra-blue/p71357115/",
        "grade": 5,
        "date": "18.11.2021",
        "text": "Переходила с XS: главные обновления по экрану, камере и батарее.Батарея живет просто невероятно долго, никогда такого апгрейда не было.Камеры, понятное дело, небо и земля.Экран очень понравился: у меня чувствительные глаза и именно этот дисплей мне зашел. После xs лично для меня - очень ощутимый апгрейд."
    },
    {
        "title": "Смартфон APPLE iPhone 13 Pro Max 128GB Sierra Blue (MLL93)",
        "author_name": "Коля",
        "url": "https://eldorado.ua/smartfon-apple-iphone-13-pro-max-128gb-sierra-blue/p71357115/",
        "grade": 5,
        "date": "17.11.2021",
        "text": "Ощущается безумно дорого!Экран полный восторг.Камера как не для фотографа меня более чем устраивает, для любителя самое то! Звук в airpods 2 стал лучше."
    },
    {
        "title": "Смартфон APPLE iPhone 13 Pro Max 128GB Sierra Blue (MLL93)",
        "author_name": "Дарья",
        "url": "https://eldorado.ua/smartfon-apple-iphone-13-pro-max-128gb-sierra-blue/p71357115/",
        "grade": 5,
        "date": "16.11.2021",
        "text": "По сравнению даже с прошлым поколением камеры сильно подтянули. Макро прямо новый мир открыл. Экран очень нравится. Особенно это заметно было, когда под рукой был мой старый iPhone . Яркость, цветопередача на уровне. 120 герц адаптивный тоже нравится, особенно как реализован именно в iPhone. Стоит взять прошлогодний и сразу понятно все."
    },
    {
        "title": "Смартфон APPLE iPhone 13 Pro Max 128GB Sierra Blue (MLL93)",
        "author_name": "Давид",
        "url": "https://eldorado.ua/smartfon-apple-iphone-13-pro-max-128gb-sierra-blue/p71357115/",
        "grade": 5,
        "date": "16.11.2021",
        "text": "Что действительно заметил: более плавный экран (все таки 120 гц), более холодный оттенок экрана, камеры крутые, особенно ширик и телевик. Автономность очень хорошая - по ощущениям. Смартфон увесистый, чувствуется вес и это то что я заметил на первый взгляд, надо по больше походить чтоб понять больше."
    },
    {
        "title": "Смартфон APPLE iPhone 13 Pro Max 128GB Sierra Blue (MLL93)",
        "author_name": "Пётр Смирнов",
        "url": "https://eldorado.ua/smartfon-apple-iphone-13-pro-max-128gb-sierra-blue/p71357115/",
        "grade": 5,
        "date": "13.11.2021",
        "text": "Отличная камера, хорошо держит батарею. Основной момент, из-за которого я покупаю уже четвертый свой айфон - длительность поддержки, на айфон 10 2017 года до сих пор выходят все обновления."
    },
    {
        "title": "Смартфон APPLE iPhone 13 Pro Max 128GB Sierra Blue (MLL93)",
        "author_name": "Евгений",
        "url": "https://eldorado.ua/smartfon-apple-iphone-13-pro-max-128gb-sierra-blue/p71357115/",
        "grade": 5,
        "date": "13.11.2021",
        "text": "Софт точно такой же, как и на более ранних моделях, а по железу апгрейды значительные. Тем, у кого телефон старше, как было в моем случае, уже имеет смысл подумать и расставить приоритеты."
    },
    {
        "title": "Смартфон APPLE iPhone 13 Pro Max 128GB Sierra Blue (MLL93)",
        "author_name": "Аня",
        "url": "https://eldorado.ua/smartfon-apple-iphone-13-pro-max-128gb-sierra-blue/p71357115/",
        "grade": 5,
        "date": "04.11.2021",
        "text": "Подскажите, пожалуйста, дату следующей поставки"
    }
]